Workbook

Sheet Products
A1: Product_ID | B1: Product_Name | C1: Type | D1: Supplier
A2: PMS001 | B2: PMS | C2: Super | D2: Fuel Trade
A3: AGO002 | B3: AGO | C3: Diesel | D3: Fuel Trade

Sheet Attendants
A1: Attendant_ID | B1: Attendant_Name | C1: Gender | D1: Contact | E1: Employment_Status
A2: RITA001 | B2: Rita Konadu | C2: F | D2: 596064379 | E2: Active
A3: ABI002 | B3: Abigail Bawah | C3: F | D3: 597257104 | E3: Active
A4: SILAS003 | B4: Silas Seibu | C4: M | D4: 541100101 | E4: Active
A5: BLESS004 | B5: Blessing Kessben | C5: M | D5: 539336747 | E5: Active

Sheet Tank_Readings
A1: Date | B1: Tank_ID | C1: Product_ID | D1: Opening_Dipping | E1: Product_Received | F1: Stock_on_Hand | G1: Closing_Dipping | H1: Tank_sales | I1: Pump_Sales | J1: Pms_Variance | K1: Variance | L1: Comments
A2: 45664 | B2: T001 | C2: PMS001 | D2: 9540 | F2: =D2+E2 -> 9540 | G2: 7500 | H2: =F2-G2 -> 2040 | I2: =Sales!I2 + Sales!I3 -> 2025.01 | J2: =I2-H2 -> -14.99 | L2: Delivery discrepancy
A3: 45664 | B3: T002 | C3: AGO002 | D3: 9720 | F3: =D3+E3 -> 9720 | G3: 8900 | H3: =F3-G3 -> 820 | I3: =SUM(Sales!I4:I7) -> 835.96 | K3: =I3-H3 -> 15.96 | L3: Meter loss
A4: 45695 | B4: T001 | C4: PMS001 | D4: 7500 | F4: =D4+E4 -> 7500 | G4: 6550 | H4: =F4-G4 -> 950 | I4: =Sales!I8 + Sales!I9 -> 983.05 | J4: =I4-H4 -> 33.05
A5: 45695 | B5: T002 | C5: AGO002 | D5: 8900 | E5: 9000 | F5: =D5+E5 -> 17900 | G5: 14990 | H5: =F5-G5 -> 2910 | I5: =SUM(Sales!I10:I13) -> 2924.05 | K5: =I5-H5 -> 14.05
A6: 45723 | B6: T001 | C6: PMS001 | D6: 6550 | F6: =D6+E6 -> 6550 | G6: 5200 | H6: =F6-G6 -> 1350 | I6: =SUM(Sales!I14:I15) -> 1364.89 | J6: =I6-H6 -> 14.89
A7: 45723 | B7: T002 | C7: AGO002 | D7: 14990 | F7: =D7+E7 -> 14990 | G7: 11920 | H7: =F7-G7 -> 3070 | I7: =SUM(Sales!I16:I19) -> 3084.57 | K7: =I7-H7 -> 14.57
A8: 45754 | B8: T001 | C8: PMS001 | D8: 5200 | F8: =D8+E8 -> 5200 | G8: 4050 | H8: =F8-G8 -> 1150 | I8: =SUM(Sales!I20:I21) -> 1135.61 | J8: =I8-H8 -> -14.39
A9: 45754 | B9: T002 | C9: AGO002 | D9: 11920 | F9: =D9+E9 -> 11920 | G9: 11420 | H9: =F9-G9 -> 500 | I9: =SUM(Sales!I22:I25) -> 516.34 | K9: =I9-H9 -> 16.34
A10: 45784 | B10: T001 | C10: PMS001 | D10: 4050 | F10: =D10+E10 -> 4050 | G10: 3010 | H10: =F10-G10 -> 1040 | I10: =SUM(Sales!I26:I27) -> 1030.67 | J10: =I10-H10 -> -9.33
A11: 45784 | B11: T002 | C11: AGO002 | D11: 11420 | F11: =D11+E11 -> 11420 | G11: 11150 | H11: =F11-G11 -> 270 | I11: =SUM(Sales!I28:I31) -> 290.29 | K11: =I11-H11 -> 20.29
A12: 45815 | B12: T001 | C12: PMS001 | D12: 3010 | F12: =D12+E12 -> 3010 | G12: 1780 | H12: =F12-G12 -> 1230 | I12: =SUM(Sales!I32:I33) -> 1261.22 | J12: =I12-H12 -> 31.22
A13: 45815 | B13: T002 | C13: AGO002 | D13: 11150 | F13: =D13+E13 -> 11150 | G13: 10750 | H13: =F13-G13 -> 400 | I13: =SUM(Sales!I34:I37) -> 393.13 | K13: =I13-H13 -> -6.87
A14: 45845 | B14: T001 | C14: PMS001 | D14: 1780 | F14: =D14+E14 -> 1780 | G14: 420 | H14: =F14-G14 -> 1360 | I14: =SUM(Sales!I38:I39) -> 1325.1 | J14: =I14-H14 -> -34.9
A15: 45845 | B15: T002 | C15: AGO002 | D15: 10750 | F15: =D15+E15 -> 10750 | G15: 9770 | H15: =F15-G15 -> 980 | I15: =SUM(Sales!I40:I43) -> 970.43 | K15: =I15-H15 -> -9.57
A16: 45876 | B16: T001 | C16: PMS001 | D16: 420 | E16: 4470 | F16: =D16+E16 -> 4890 | G16: 4120 | H16: =F16-G16 -> 770 | I16: =SUM(Sales!I44:I45) -> 794.02 | J16: =I16-H16 -> 24.02
A17: 45876 | B17: T002 | C17: AGO002 | D17: 9770 | F17: =D17+E17 -> 9770 | G17: 8180 | H17: =F17-G17 -> 1590 | I17: =SUM(Sales!I46:I49) -> 1604.01 | K17: =I17-H17 -> 14.01
A18: 45907 | B18: T001 | C18: PMS001 | D18: 4120 | E18: 13410 | F18: =D18+E18 -> 17530 | G18: 16290 | H18: =F18-G18 -> 1240 | I18: =SUM(Sales!I50:I51) -> 1241.58 | J18: =I18-H18 -> 1.58
A19: 45907 | B19: T002 | C19: AGO002 | D19: 8180 | F19: =D19+E19 -> 8180 | G19: 7110 | H19: =F19-G19 -> 1070 | I19: =SUM(Sales!I52:I55) -> 1063.44 | K19: =I19-H19 -> -6.56
A20: 45937 | B20: T001 | C20: PMS001 | D20: 16290 | F20: =D20+E20 -> 16290 | G20: 15300 | H20: =F20-G20 -> 990 | I20: =SUM(Sales!I56:I57) -> 995.74 | J20: =I20-H20 -> 5.74
A21: 45937 | B21: T002 | C21: AGO002 | D21: 7110 | E21: 8940 | F21: =D21+E21 -> 16050 | G21: 15420 | H21: =F21-G21 -> 630 | I21: =SUM(Sales!I58:I61) -> 634.07 | K21: =I21-H21 -> 4.07
A22: 45968 | B22: T001 | C22: PMS001 | D22: 15300 | F22: =D22+E22 -> 15300 | G22: 13810 | H22: =F22-G22 -> 1490 | I22: =SUM(Sales!I62:I63) -> 1463.38 | J22: =I22-H22 -> -26.62
A23: 45968 | B23: T002 | C23: AGO002 | D23: 15420 | F23: =D23+E23 -> 15420 | G23: 14920 | H23: =F23-G23 -> 500 | I23: =SUM(Sales!I64:I67) -> 500.67 | K23: =I23-H23 -> 0.67
A24: 45998 | B24: T001 | C24: PMS001 | D24: 13810 | F24: =D24+E24 -> 13810 | G24: 12630 | H24: =F24-G24 -> 1180 | I24: =SUM(Sales!I68:I69) -> 1169.91 | J24: =I24-H24 -> -10.09
A25: 45998 | B25: T002 | C25: AGO002 | D25: 14920 | E25: 4500 | F25: =D25+E25 -> 19420 | G25: 19180 | H25: =F25-G25 -> 240 | I25: =SUM(Sales!I70:I73) -> 279.12 | K25: =I25-H25 -> 39.12
A26: 13/07/2025 | B26: T001 | C26: PMS001 | D26: 12630 | F26: =D26+E26 -> 12630 | G26: 11530 | H26: =F26-G26 -> 1100 | I26: =SUM(Sales!I74:I75) -> 1145.85 | J26: =I26-H26 -> 45.85
A27: 13/07/2025 | B27: T002 | C27: AGO002 | D27: 19180 | F27: =D27+E27 -> 19180 | G27: 18700 | H27: =F27-G27 -> 480 | I27: =SUM(Sales!I76:I79) -> 516.54 | K27: =I27-H27 -> 36.54
A28: 14/07/2025 | B28: T001 | C28: PMS001 | D28: 11530 | F28: =D28+E28 -> 11530 | G28: 10150 | H28: =F28-G28 -> 1380 | I28: =SUM(Sales!I80:I81) -> 1378.05 | J28: =I28-H28 -> -1.95
A29: 14/07/2025 | B29: T002 | C29: AGO002 | D29: 18700 | F29: =D29+E29 -> 18700 | G29: 17850 | H29: =F29-G29 -> 850 | I29: =SUM(Sales!I82:I85) -> 785.33 | K29: =I29-H29 -> -64.67
A30: 15/07/2025 | B30: T001 | C30: PMS001 | D30: 10150 | F30: =D30+E30 -> 10150 | G30: 7950 | H30: =F30-G30 -> 2200 | I30: =SUM(Sales!I86:I87) -> 2218.38 | J30: =I30-H30 -> 18.38
A31: 15/07/2025 | B31: T002 | C31: AGO002 | D31: 17850 | F31: =D31+E31 -> 17850 | G31: 15800 | H31: =F31-G31 -> 2050 | I31: =SUM(Sales!I88:I91) -> 2025.7 | K31: =I31-H31 -> -24.3
A32: 16/07/2025 | B32: T001 | C32: PMS001 | D32: 7950 | F32: =D32+E32 -> 7950 | G32: 7240 | H32: =F32-G32 -> 710 | I32: =SUM(Sales!I92:I93) -> 698.21 | J32: =I32-H32 -> -11.79
A33: 16/07/2025 | B33: T002 | C33: AGO002 | D33: 15800 | F33: =D33+E33 -> 15800 | G33: 15420 | H33: =F33-G33 -> 380 | I33: =SUM(Sales!I94:I97) -> 374.31 | K33: =I33-H33 -> -5.69
A34: 17/07/2025 | B34: T001 | C34: PMS001 | D34: 7240 | E34: 4500 | F34: =D34+E34 -> 11740 | G34: 10400 | H34: =F34-G34 -> 1340 | I34: =SUM(Sales!I98:I99) -> 1344.63 | J34: =I34-H34 -> 4.63
A35: 17/07/2025 | B35: T002 | C35: AGO002 | D35: 15420 | F35: =D35+E35 -> 15420 | G35: 14900 | H35: =F35-G35 -> 520 | I35: =SUM(Sales!I100:I103) -> 527.5 | K35: =I35-H35 -> 7.5
A36: 18/07/2025 | B36: T001 | C36: PMS001 | D36: 10400 | F36: =D36+E36 -> 10400 | G36: 9290 | H36: =F36-G36 -> 1110 | I36: =SUM(Sales!I104:I105) -> 1112.35 | J36: =I36-H36 -> 2.35
A37: 18/07/2025 | B37: T002 | C37: AGO002 | D37: 14900 | F37: =D37+E37 -> 14900 | G37: 13240 | H37: =F37-G37 -> 1660 | I37: =SUM(Sales!I106:I109) -> 1678.25 | K37: =I37-H37 -> 18.25
A38: 19/07/2025 | B38: T001 | C38: PMS001 | D38: 9290 | F38: =D38+E38 -> 9290 | G38: 8300 | H38: =F38-G38 -> 990 | I38: =SUM(Sales!I110:I111) -> 969.56 | J38: =I38-H38 -> -20.44
A39: 19/07/2025 | B39: T002 | C39: AGO002 | D39: 13240 | F39: =D39+E39 -> 13240 | G39: 12840 | H39: =F39-G39 -> 400 | I39: =SUM(Sales!I112:I115) -> 401.43 | K39: =I39-H39 -> 1.43
A40: 20/07/2025 | B40: T001 | C40: PMS001 | D40: 8300 | F40: =D40+E40 -> 8300 | G40: 7080 | H40: =F40-G40 -> 1220 | I40: =SUM(Sales!I116:I117) -> 1267.18 | J40: =I40-H40 -> 47.18
A41: 20/07/2025 | B41: T002 | C41: AGO002 | D41: 12840 | F41: =D41+E41 -> 12840 | G41: 8020 | H41: =F41-G41 -> 4820 | I41: =SUM(Sales!I118:I121) -> 4892.81 | K41: =I41-H41 -> 72.81
A42: 21/07/2025 | B42: T001 | C42: PMS001 | D42: 7080 | F42: =D42+E42 -> 7080 | G42: 5610 | H42: =F42-G42 -> 1470 | I42: =SUM(Sales!I122:I123) -> 1458.5 | J42: =I42-H42 -> -11.5
A43: 21/07/2025 | B43: T002 | C43: AGO002 | D43: 8020 | F43: =D43+E43 -> 8020 | G43: 7550 | H43: =F43-G43 -> 470 | I43: =SUM(Sales!I124:I127) -> 444.79 | K43: =I43-H43 -> -25.21
A44: 22/07/2025 | B44: T001 | C44: PMS001 | D44: 5610 | F44: =D44+E44 -> 5610 | G44: 4310 | H44: =F44-G44 -> 1300 | I44: =SUM(Sales!I128:I129) -> 1304.56 | J44: =I44-H44 -> 4.56
A45: 22/07/2025 | B45: T002 | C45: AGO002 | D45: 7550 | F45: =D45+E45 -> 7550 | G45: 6920 | H45: =F45-G45 -> 630 | I45: =SUM(Sales!I130:I133) -> 628.65 | K45: =I45-H45 -> -1.35
A46: 23/07/2025 | B46: T001 | C46: PMS001 | D46: 4310 | E46: 8950 | F46: =D46+E46 -> 13260 | G46: 12050 | H46: =F46-G46 -> 1210 | I46: =SUM(Sales!I134:I135) -> 1163.72 | J46: =I46-H46 -> -46.28
A47: 23/07/2025 | B47: T002 | C47: AGO002 | D47: 6920 | F47: =D47+E47 -> 6920 | G47: 5900 | H47: =F47-G47 -> 1020 | I47: =SUM(Sales!I136:I139) -> 1041.17 | K47: =I47-H47 -> 21.17
A48: 24/07/2025 | B48: T001 | C48: PMS001 | D48: 12050 | F48: =D48+E48 -> 12050 | G48: 10800 | H48: =F48-G48 -> 1250 | I48: =SUM(Sales!I140:I141) -> 1246.01 | J48: =I48-H48 -> -3.99
A49: 24/07/2025 | B49: T002 | C49: AGO002 | D49: 5900 | E49: 13500 | F49: =D49+E49 -> 19400 | G49: 16900 | H49: =F49-G49 -> 2500 | I49: =SUM(Sales!I142:I145) -> 2417.4 | K49: =I49-H49 -> -82.6
A50: 25/07/2025 | B50: T001 | C50: PMS001 | D50: 10800 | F50: =D50+E50 -> 10800 | G50: 9950 | H50: =F50-G50 -> 850 | I50: =SUM(Sales!I146:I147) -> 897.39 | J50: =I50-H50 -> 47.39
A51: 25/07/2025 | B51: T002 | C51: AGO002 | D51: 16900 | F51: =D51+E51 -> 16900 | G51: 16330 | H51: =F51-G51 -> 570 | I51: =SUM(Sales!I148:I151) -> 528.26 | K51: =I51-H51 -> -41.74
A52: 26/07/2025 | B52: T001 | C52: PMS001 | D52: 9950 | F52: =D52+E52 -> 9950 | G52: 8790 | H52: =F52-G52 -> 1160 | I52: =SUM(Sales!I152:I153) -> 1115.26 | J52: =I52-H52 -> -44.74
A53: 26/07/2025 | B53: T002 | C53: AGO002 | D53: 16330 | F53: =D53+E53 -> 16330 | G53: 13920 | H53: =F53-G53 -> 2410 | I53: =SUM(Sales!I154:I157) -> 2438.4 | K53: =I53-H53 -> 28.4
A54: 27/07/2025 | B54: T001 | C54: PMS001 | D54: 8790 | F54: =D54+E54 -> 8790 | G54: 7400 | H54: =F54-G54 -> 1390 | I54: =SUM(Sales!I158:I159) -> 1401.19 | J54: =I54-H54 -> 11.19
A55: 27/07/2025 | B55: T002 | C55: AGO002 | D55: 13920 | F55: =D55+E55 -> 13920 | G55: 12550 | H55: =F55-G55 -> 1370 | I55: =SUM(Sales!I160:I163) -> 1365.74 | K55: =I55-H55 -> -4.26
A56: 28/07/2025 | B56: T001 | C56: PMS001 | D56: 7400 | F56: =D56+E56 -> 7400 | G56: 5930 | H56: =F56-G56 -> 1470 | I56: =SUM(Sales!I164:I165) -> 1471.05 | J56: =I56-H56 -> 1.05
A57: 28/07/2025 | B57: T002 | C57: AGO002 | D57: 12550 | F57: =D57+E57 -> 12550 | G57: 12000 | H57: =F57-G57 -> 550 | I57: =SUM(Sales!I166:I169) -> 527.17 | K57: =I57-H57 -> -22.83
A58: 29/07/2025 | B58: T001 | C58: PMS001 | D58: 5930 | F58: =D58+E58 -> 5930 | G58: 4620 | H58: =F58-G58 -> 1310 | I58: =SUM(Sales!I170:I171) -> 1293.3 | J58: =I58-H58 -> -16.7
A59: 29/07/2025 | B59: T002 | C59: AGO002 | D59: 12000 | F59: =D59+E59 -> 12000 | G59: 11590 | H59: =F59-G59 -> 410 | I59: =SUM(Sales!I172:I175) -> 427.05 | K59: =I59-H59 -> 17.05
A60: 30/07/2025 | B60: T001 | C60: PMS001 | D60: 4620 | E60: 13430 | F60: =D60+E60 -> 18050 | G60: 17000 | H60: =F60-G60 -> 1050 | I60: =SUM(Sales!I176:I177) -> 1064.44 | J60: =I60-H60 -> 14.44
A61: 30/07/2025 | B61: T002 | C61: AGO002 | D61: 11590 | E61: 4500 | F61: =D61+E61 -> 16090 | G61: 15600 | H61: =F61-G61 -> 490 | I61: =SUM(Sales!I178:I181) -> 443.99 | K61: =I61-H61 -> -46.01
A62: 31/07/2025 | B62: T001 | C62: PMS001 | D62: 17000 | F62: =D62+E62 -> 17000 | G62: 15800 | H62: =F62-G62 -> 1200 | I62: =SUM(Sales!I182:I183) -> 1185.88 | J62: =I62-H62 -> -14.12
A63: 31/07/2025 | B63: T002 | C63: AGO002 | D63: 15600 | F63: =D63+E63 -> 15600 | G63: 14000 | H63: =F63-G63 -> 1600 | I63: =SUM(Sales!I184:I187) -> 1641.35 | K63: =I63-H63 -> 41.35

Sheet Corporate_Credit_Sales
A1: Credit_ID | B1: Date | C1: Customer_Name | D1: BRV_Number | E1: Product_ID | F1: Product_Name | G1: Litres | H1: Litre_Price | I1: Amount | J1: Payment_Status
A2: CRKRL004 | B2: 45695 | C2: Kraft Logisto | D2: GT-9967-16 | E2: AGO002 | F2: AGO | G2: 392.16 | H2: 12.5 | I2: =G2*H2 -> 4902 | J2: Settle with head office
A3: CRCLL001 | B3: 45723 | C3: Carbon Logistics | D3: GN-647-18 | E3: AGO002 | F3: AGO | G3: 346.08 | H3: 12.5 | I3: =G3*H3 -> 4326 | J3: Settle with head office
A4: CRCLL001 | B4: 45907 | C4: Carbon Logistics | D4: GN-647-18 | E4: AGO002 | F4: AGO | G4: 346.82 | H4: 13.2 | I4: =G4*H4 -> 4578.024 | J4: Settle with head office
A5: CRAB002 | B5: 23/07/2025 | C5: Ali Abubakar | D5: GX-4293-14 | E5: AGO002 | F5: AGO | G5: 687.54 | H5: 14.2 | I5: =G5*H5 -> 9763.068 | J5: Settle with head office
A6: CRMO007 | B6: 30/07/2025 | C6: Musah Osumanu | D6: GW-1939-17 | E6: AGO002 | F6: AGO | G6: 180 | H6: 14.2 | I6: =G6*H6 -> 2556 | J6: Settle with head office

Sheet Credit_Sales
A1: Credit_ID | B1: Date | C1: Customer_Name | D1: Car_Number/Person_Nmae | E1: Product_ID | F1: Product_Name | G1: Litres | H1: Litre_Price | I1: Amount | J1: Payment_Status
A2: CRKM001 | B2: 45695 | C2: Klean Metro | D2: Agya Osei | E2: AGO002 | F2: AGO | G2: 72 | H2: 12.5 | I2: =G2*H2 -> 900 | J2: Paid
A3: CRKM001 | B3: 45845 | C3: Klean Metro | D3: Agya Osei | E3: AGO002 | F3: AGO | G3: 69.29 | H3: 12.99 | I3: =G3*H3 -> 900.0771 | J3: Paid
A4: CRKM001 | B4: 15/07/2025 | C4: Klean Metro | D4: Agya Osei | E4: AGO002 | F4: AGO | G4: 68.18 | H4: 13.2 | I4: =G4*H4 -> 899.976 | J4: Paid

Sheet Expenses
A1: Expense_ID | B1: Date | C1: Category | D1: Description | E1: Amount | F1: Payment_Method | G1: Approved_By
A2: EX001 | B2: 45664 | C2: Transportation | D2: TnT to Bank | E2: 50 | F2: Cash | G2: Manager
A3: EX002 | B3: 45664 | C3: Head Office Fuel | D3: office car | E3: 890 | F3: settle by head office | G3: Auditor
A4: EX001 | B4: 45695 | C4: Transportation | D4: TnT to Bank | E4: 50 | F4: Cash | G4: Manager
A5: EX003 | B5: 45723 | C5: Housekeeping | D5: Detergents | E5: 600 | F5: Cash | G5: Manager
A6: EXP04 | B6: 45723 | C6: Other | D6: outstation to Ops | E6: 750 | F6: Mobil money | G6: Ops Manager
A7: EX002 | B7: 45815 | C7: Head Office Fuel | D7: office car | E7: 891 | F7: settle by head office | G7: Auditor
A8: EX001 | B8: 45815 | C8: Transportation | D8: TnT to Bank | E8: 50 | F8: Cash | G8: Manager
A9: EX005 | B9: 45815 | C9: Stationery | D9: Photocopies and books | E9: 300 | F9: Cash | G9: Manager
A10: EX006 | B10: 45845 | C10: Gen set | D10: Fuel for Gen set | E10: 400 | F10: Cash | G10: Manager
A11: EX001 | B11: 45845 | C11: Transportation | D11: TnT to Bank | E11: 50 | F11: Cash | G11: Manager
A12: EX006 | B12: 45876 | C12: Gen set | D12: Fuel for Gen set | E12: 500 | F12: Cash | G12: Manager
A13: EX001 | B13: 45876 | C13: Transportation | D13: TnT to Bank | E13: 50 | F13: Cash | G13: Manager
... A15: EX001 | B15: 45937 | C15: Transportation | D15: TnT to Bank | E15: 50 | F15: Cash | G15: Manager
A16: EX001 | B16: 13/07/2025 | C16: Transportation | D16: TnT to Bank | E16: 50 | F16: Cash | G16: Manager
A17: EX006 | B17: 14/07/2025 | C17: Gen set | D17: Fuel for Gen set | E17: 400 | F17: Cash | G17: Manager
A18: EX001 | B18: 14/07/2025 | C18: Transportation | D18: TnT to Bank | E18: 50 | F18: Cash | G18: Manager
A19: EX001 | B19: 15/07/2025 | C19: Transportation | D19: TnT to Bank | E19: 50 | F19: Cash | G19: Manager
A20: EX001 | B20: 16/07/2025 | C20: Transportation | D20: TnT to Bank | E20: 50 | F20: Cash | G20: Manager
A21: EX001 | B21: 17/07/2025 | C21: Transportation | D21: TnT to Bank | E21: 50 | F21: Cash | G21: Manager
A22: EX001 | B22: 20/07/2025 | C22: Transportation | D22: TnT to Bank | E22: 50 | F22: Cash | G22: Manager
A23: EX001 | B23: 21/07/2025 | C23: Transportation | D23: TnT to Bank | E23: 50 | F23: Cash | G23: Manager
A24: EX001 | B24: 22/07/2025 | C24: Transportation | D24: TnT to Bank | E24: 50 | F24: Cash | G24: Manager
A25: EX001 | B25: 23/07/2025 | C25: Transportation | D25: TnT to Bank | E25: 50 | F25: Cash | G25: Manager
A26: EX001 | B26: 24/07/2025 | C26: Transportation | D26: TnT to Bank | E26: 50 | F26: Cash | G26: Manager
A27: EX001 | B27: 27/07/2025 | C27: Transportation | D27: TnT to Bank | E27: 50 | F27: Cash | G27: Manager
... A33: EX001 | B33: 31/07/2025 | C33: Transportation | D33: TnT to Bank | E33: 50 | F33: Cash | G33: Manager

Sheet Transporters
A1: Date | B1: BRV_Number | C1: Transporter_Name | D1: Transporter_ID | E1: Product_ID | F1: Invoice_Number | G1: Product_Type | H1: Loaded_Quantity | I1: Discharged_Quantity | J1: Initial_Dipping | K1: Final_Dipping | L1: Pms_Variance | M1: Ago_Variance | N1: Unit_Price | O1: Amount_Product
A2: 45695 | B2: GT-9967-16 | C2: Kraft Logisto | D2: TRKL003 | E2: AGO002 | F2: 6236 | G2: AGO | H2: 9000 | I2: 9000 | J2: 8580 | K2: 17580 | M2: =H2-I2 -> 0 | N2: 12.5 | O2: =I2*N2 -> 112500
A3: 45876 | B3: GW-9421-X | C3: Emmak Logistic | D3: TREL002 | E3: PMS001 | F3: 6477 | G3: PMS | H3: 4500 | I3: 4470 | J3: 220 | K3: 4690 | L3: =H3-I3 -> 30 | N3: 11.6 | O3: =I3*N3 -> 51852
A4: 45907 | B4: GN-647-18 | C4: Carbon Logistics | D4: TRCLL001 | E4: PMS001 | F4: 6491 | G4: PMS | H4: 13500 | I4: 13410 | J4: 3750 | K4: 17160 | L4: =H4-I4 -> 90 | N4: 11.6 | O4: =I4*N4 -> 155556
A5: 45937 | B5: AS-4739-17 | C5: Pony Com. Ltd | D5: TRPCL006 | E5: AGO002 | F5: 6402 | G5: AGO | H5: 9000 | I5: 8940 | J5: 7040 | K5: 15980 | M5: =H5-I5 -> 60 | N5: 13.2 | O5: =I5*N5 -> 118008
A6: 45998 | B6: GN-647-18 | C6: Carbon Logistics | D6: TRCLL001 | E6: AGO002 | F6: 8859 | G6: AGO | H6: 4500 | I6: 4500 | J6: 14920 | K6: 19420 | N6: 13.2 | O6: =I6*N6 -> 59400
A7: 17/07/2025 | B7: GN-9644-18 | C7: Astral Energy | D7: TRAE009 | E7: PMS001 | F7: 6447 | G7: PMS | H7: 4500 | I7: 4500 | J7: 6610 | K7: 11110 | N7: 12.6 | O7: =I7*N7 -> 56700
A8: 23/07/2025 | B8: GX-4293-14 | C8: Ali Abubakar | D8: TRAA0010 | E8: PMS001 | F8: 5945 | G8: PMS | H8: 9000 | I8: 8950 | J8: 3800 | K8: 12750 | L8: =H8-I8 -> 50 | N8: 12.6 | O8: =I8*N8 -> 112770
A9: 24/07/2025 | B9: GN-5653-20 | C9: Kraft Logisto | D9: TRKL003 | E9: AGO002 | F9: 5933 | G9: AGO | H9: 13500 | I9: 13500 | J9: 5900 | K9: 19400 | M9: =H9-I9 -> 0 | N9: 14.2 | O9: =I9*N9 -> 191700
A10: 30/07/2025 | B10: GW-1939-17 | C10: Mambah Gas | D10: TRMG007 | E10: AGO002 | F10: 8882 | G10: AGO | H10: 4500 | I10: 4500 | J10: 11520 | K10: 16020 | M10: =H10-I10 -> 0 | N10: 14.2 | O10: =I10*N10 -> 63900
A11: 30/07/2025 | B11: GW-1939-17 | C11: musah osumanu | D11: TRMO004 | E11: PMS001 | F11: 8877 | G11: PMS | H11: 13500 | I11: 13430 | J11: 4500 | K11: 13500 | L11: =H11-I11 -> 70 | N11: 12.6 | O11: =I11*N11 -> 169218

Sheet Calendar
A1: Date | B1: Year | C1: Month | D1: Month_Name | E1: Day | F1: Day_Name
A2: 45839 | B2: 2025 | C2: 7 | D2: July | E2: 1 | F2: Tuesday
A3: 45840 | B3: 2025 | C3: 7 | D3: July | E3: 2 | F3: Wednesday
A4: 45841 | B4: 2025 | C4: 7 | D4: July | E4: 3 | F4: Thursday
A5: 45842 | B5: 2025 | C5: 7 | D5: July | E5: 4 | F5: Friday
A6: 45843 | B6: 2025 | C6: 7 | D6: July | E6: 5 | F6: Saturday
A7: 45844 | B7: 2025 | C7: 7 | D7: July | E7: 6 | F7: Sunday
A8: 45845 | B8: 2025 | C8: 7 | D8: July | E8: 7 | F8: Monday
A9: 45846 | B9: 2025 | C9: 7 | D9: July | E9: 8 | F9: Tuesday
A10: 45847 | B10: 2025 | C10: 7 | D10: July | E10: 9 | F10: Wednesday
A11: 45848 | B11: 2025 | C11: 7 | D11: July | E11: 10 | F11: Thursday
A12: 45849 | B12: 2025 | C12: 7 | D12: July | E12: 11 | F12: Friday
A13: 45850 | B13: 2025 | C13: 7 | D13: July | E13: 12 | F13: Saturday
... A31: 45868 | B31: 2025 | C31: 7 | D31: July | E31: 30 | F31: Wednesday

Sheet Sales
A1: Date | B1: Shift_Day | C1: Attendant_ID | D1: Product_ID | E1: Dispenser_Nozzle_No | F1: Opening_Meter_Reading | G1: Closing_Meter_Reading | H1: Return_to_Tank | I1: Litres_Sold | J1: Unit_Price _Perliter | K1: Total_Sales_Amount | L1: Pms_Total_Sales | M1: AGO_Total_Sales | N1: Total_Sales_All | O1: Expenses_TnT | P1: Expenses_H.O_Fuel | Q1: Expenses_Dealer_Comm/Salaries | R1: Expenses_Hse_Detergents | S1: Expenses_Stationery | T1: Expenses_Utilities | U1: Expenses_other | V1: Credit_Sales | W1: TxT_Bank | X1: Actual_Banking | Y1: Banking_Variance
A2: 45664 | B2: Tuesday | C2: SILAS003 | D2: PMS001 | E2: 1 | F2: 347417.86 | G2: 348291.51 | I2: =G2-F2 -> 873.65 | J2: 10.99 | K2: =I2*J2 -> 9601.4135 | L2: =K2+K3 -> 22254.86 | M2: =K4+K5+K6+K7 -> 10449.5 | N2: =SUM(L2:M2) -> 32704.36 | O2: 50 | P2: 890 | W2: =N2-O2-P2-Q2-R2-S2-T2-U2-V2 -> 31764.36 | X2: 31765 | Y2: =X2-W2 -> 0.6401
A3: 45664 | B3: Tuesday | C3: SILAS003 | D3: PMS001 | E3: 2 | F3: 553184.26 | G3: 554335.62 | I3: =G3-F3 -> 1151.36 | J3: 10.99 | K3: =I3*J3 -> 12653.446
A4: 45664 | B4: Tuesday | C4: ABI002 | D4: AGO002 | E4: 1 | F4: 283361.49 | G4: 283361.49 | I4: =G4-F4 -> 0 | J4: 12.5 | K4: =I4*J4 -> 0
A5: 45664 | B5: Tuesday | C5: ABI002 | D5: AGO002 | E5: 2 | F5: 407356.75 | G5: 407559.16 | I5: =G5-F5 -> 202.41 | J5: 12.5 | K5: =I5*J5 -> 2530.125
A6: 45664 | B6: Tuesday | C6: ABI002 | D6: AGO002 | E6: 3 | F6: 367111.54 | G6: 367538.61 | I6: =G6-F6 -> 427.07 | J6: 12.5 | K6: =I6*J6 -> 5338.375
A7: 45664 | B7: Tuesday | C7: ABI002 | D7: AGO002 | E7: 4 | F7: 520674.58 | G7: 520881.06 | I7: =G7-F7 -> 206.48 | J7: 12.5 | K7: =I7*J7 -> 2581
A8: 45695 | B8: Wednes | C8: ABI002 | D8: PMS001 | E8: 1 | F8: 348291.51 | G8: 348552.17 | I8: =G8-F8 -> 260.66 | J8: 10.99 | K8: =I8*J8 -> 2864.6534 | L8: =K8+K9 -> 10803.719 | M8: =K10+K11+K12+K13 -> 36550.625 | N8: =SUM(L8:M8) -> 47354.345 | O8: 50 | V8: 5802 | W8: =N8-O8-P8-Q8-R8-S8-T8-U8-V8 -> 41502.345 | X8: 41503 | Y8: =X8-W8 -> 0.6555
A9: 45695 | B9: Wednes | C9: ABI002 | D9: PMS001 | E9: 2 | F9: 554335.62 | G9: 555058.01 | I9: =G9-F9 -> 722.39 | J9: 10.99 | K9: =I9*J9 -> 7939.0661
A10: 45695 | B10: Wednes | C10: SILAS003 | D10: AGO002 | E10: 1 | F10: 283361.49 | G10: 283922.29 | I10: =G10-F10 -> 560.8 | J10: 12.5 | K10: =I10*J10 -> 7010
A11: 45695 | B11: Wednes | C11: SILAS003 | D11: AGO002 | E11: 2 | F11: 407559.16 | G11: 407983.7 | I11: =G11-F11 -> 424.54 | J11: 12.5 | K11: =I11*J11 -> 5306.75
A12: 45695 | B12: Wednes | C12: SILAS003 | D12: AGO002 | E12: 3 | F12: 367538.61 | G12: 368416.65 | I12: =G12-F12 -> 878.04 | J12: 12.5 | K12: =I12*J12 -> 10975.5
A13: 45695 | B13: Wednes | C13: SILAS003 | D13: AGO002 | E13: 4 | F13: 520881.06 | G13: 521941.73 | I13: =G13-F13 -> 1060.67 | J13: 12.5 | K13: =I13*J13 -> 13258.375
A14: 45723 | B14: Thursday | C14: RITA001 | D14: PMS001 | E14: 1 | F14: 348552.17 | G14: 349139.53 | I14: =G14-F14 -> 587.36 | J14: 10.99 | K14: =I14*J14 -> 6455.0864 | L14: =K14+K15 -> 15000.141 | M14: =K16+K17+K18+K19 -> 38557.125 | N14: =SUM(L14:M14) -> 53557.266 | R14: 600 | U14: 750 | V14: 4326 | W14: =N14-O14-P14-Q14-R14-S14-T14-U14-V14 -> 47881.266 | X14: 47882 | Y14: =X14-W14 -> 0.7339
A15: 45723 | B15: Thursday | C15: RITA001 | D15: PMS001 | E15: 2 | F15: 555058.01 | G15: 555835.54 | I15: =G15-F15 -> 777.53 | J15: 10.99 | K15: =I15*J15 -> 8545.0547
A16: 45723 | B16: Thursday | C16: RITA001 | D16: AGO002 | E16: 1 | F16: 283922.29 | G16: 285206.16 | I16: =G16-F16 -> 1283.87 | J16: 12.5 | K16: =I16*J16 -> 16048.375
A17: 45723 | B17: Thursday | C17: BLESS004 | D17: AGO002 | E17: 2 | F17: 407983.7 | G17: 408023.7 | I17: =G17-F17 -> 40 | J17: 12.5 | K17: =I17*J17 -> 500
A18: 45723 | B18: Thursday | C18: BLESS004 | D18: AGO002 | E18: 3 | F18: 368416.65 | G18: 369888.15 | I18: =G18-F18 -> 1471.5 | J18: 12.5 | K18: =I18*J18 -> 18393.75
A19: 45723 | B19: Thursday | C19: BLESS004 | D19: AGO002 | E19: 4 | F19: 521941.73 | G19: 522230.93 | I19: =G19-F19 -> 289.2 | J19: 12.5 | K19: =I19*J19 -> 3615
A20: 45754 | B20: Friday | C20: BLESS004 | D20: PMS001 | E20: 1 | F20: 349139.53 | G20: 349713.42 | I20: =G20-F20 -> 573.89 | J20: 10.99 | K20: =I20*J20 -> 6307.0511 | L20: =K20+K21 -> 12480.354 | M20: =K22+K23+K24+K25 -> 6707.2566 | N20: =SUM(L20:M20) -> 19187.61 | W20: =N20-O20-P20-Q20-R20-S20-T20-U20-V20 -> 19187.61 | X20: 19188 | Y20: =X20-W20 -> 0.3895
A21: 45754 | B21: Friday | C21: BLESS004 | D21: PMS001 | E21: 2 | F21: 555835.54 | G21: 556397.26 | I21: =G21-F21 -> 561.72 | J21: 10.99 | K21: =I21*J21 -> 6173.3028
A22: 45754 | B22: Friday | C22: RITA001 | D22: AGO002 | E22: 1 | F22: 285206.16 | G22: 285282.38 | I22: =G22-F22 -> 76.22 | J22: 12.99 | K22: =I22*J22 -> 990.0978
A23: 45754 | B23: Friday | C23: RITA001 | D23: AGO002 | E23: 2 | F23: 408023.7 | G23: 408099.77 | I23: =G23-F23 -> 76.07 | J23: 12.99 | K23: =I23*J23 -> 988.1493
A24: 45754 | B24: Friday | C24: RITA001 | D24: AGO002 | E24: 3 | F24: 369888.15 | G24: 369996.72 | I24: =G24-F24 -> 108.57 | J24: 12.99 | K24: =I24*J24 -> 1410.3243
A25: 45754 | B25: Friday | C25: RITA001 | D25: AGO002 | E25: 4 | F25: 522230.93 | G25: 522486.41 | I25: =G25-F25 -> 255.48 | J25: 12.99 | K25: =I25*J25 -> 3318.6852
A26: 45784 | B26: Saturday | C26: SILAS003 | D26: PMS001 | E26: 1 | F26: 349713.42 | G26: 350037.9 | I26: =G26-F26 -> 324.48 | J26: 10.99 | K26: =I26*J26 -> 3566.0352 | L26: =K26+K27 -> 11327.063 | M26: =K28+K29+K30+K31 -> 3770.8671 | N26: =SUM(L26:M26) -> 15097.93 | W26: =N26-O26-P26-Q26-R26-S26-T26-U26-V26 -> 15097.93 | X26: 15098 | Y26: =X26-W26 -> 0.0696
A27: 45784 | B27: Saturday | C27: SILAS003 | D27: PMS001 | E27: 2 | F27: 556397.26 | G27: 557103.45 | I27: =G27-F27 -> 706.19 | J27: 10.99 | K27: =I27*J27 -> 7761.0281
A28: 45784 | B28: Saturday | C28: ABI002 | D28: AGO002 | E28: 1 | F28: 285282.38 | G28: 285282.38 | I28: =G28-F28 -> 0 | J28: 12.99 | K28: =I28*J28 -> 0
A29: 45784 | B29: Saturday | C29: ABI002 | D29: AGO002 | E29: 2 | F29: 408099.77 | G29: 408139.81 | I29: =G29-F29 -> 40.04 | J29: 12.99 | K29: =I29*J29 -> 520.1196
A30: 45784 | B30: Saturday | C30: ABI002 | D30: AGO002 | E30: 3 | F30: 369996.72 | G30: 370140.72 | I30: =G30-F30 -> 144 | J30: 12.99 | K30: =I30*J30 -> 1870.56
A31: 45784 | B31: Saturday | C31: ABI002 | D31: AGO002 | E31: 4 | F31: 522486.41 | G31: 522592.66 | I31: =G31-F31 -> 106.25 | J31: 12.99 | K31: =I31*J31 -> 1380.1875
A32: 45815 | B32: Sunday | C32: ABI002 | D32: PMS001 | E32: 1 | F32: 350037.9 | G32: 350508.35 | I32: =G32-F32 -> 470.45 | J32: 10.99 | K32: =I32*J32 -> 5170.2455 | L32: =K32+K33 -> 13860.808 | M32: =K34+K35+K36+K37 -> 5106.7587 | N32: =SUM(L32:M32) -> 18967.567 | O32: 50 | P32: 891 | S32: 300 | W32: =N32-O32-P32-Q32-R32-S32-T32-U32-V32 -> 17726.567 | X32: 17727 | Y32: =X32-W32 -> 0.4335
A33: 45815 | B33: Sunday | C33: ABI002 | D33: PMS001 | E33: 2 | F33: 557103.45 | G33: 557894.22 | I33: =G33-F33 -> 790.77 | J33: 10.99 | K33: =I33*J33 -> 8690.5623
A34: 45815 | B34: Sunday | C34: SILAS003 | D34: AGO002 | E34: 1 | F34: 285282.38 | G34: 285282.38 | I34: =G34-F34 -> 0 | J34: 12.99 | K34: =I34*J34 -> 0
A35: 45815 | B35: Sunday | C35: SILAS003 | D35: AGO002 | E35: 2 | F35: 408139.81 | G35: 408155.21 | I35: =G35-F35 -> 15.4 | J35: 12.99 | K35: =I35*J35 -> 200.046
A36: 45815 | B36: Sunday | C36: SILAS003 | D36: AGO002 | E36: 3 | F36: 370140.72 | G36: 370421.35 | I36: =G36-F36 -> 280.63 | J36: 12.99 | K36: =I36*J36 -> 3645.3837
A37: 45815 | B37: Sunday | C37: SILAS003 | D37: AGO002 | E37: 4 | F37: 522592.66 | G37: 522689.76 | I37: =G37-F37 -> 97.1 | J37: 12.99 | K37: =I37*J37 -> 1261.329
A38: 45845 | B38: Monday | C38: RITA001 | D38: PMS001 | E38: 1 | F38: 350508.35 | G38: 350963.05 | H38: 10 | I38: =G38-F38-H38 -> 444.7 | J38: 10.99 | K38: =I38*J38 -> 4887.253 | L38: =K38+K39 -> 14562.849 | M38: =K40+K41+K42+K43 -> 12605.886 | N38: =SUM(L38:M38) -> 27168.735 | O38: 50 | U38: 400 | V38: 900 | W38: =N38-O38-P38-Q38-R38-S38-T38-U38-V38 -> 25818.735 | X38: 25819 | Y38: =X38-W38 -> 0.2653
A39: 45845 | B39: Monday | C39: RITA001 | D39: PMS001 | E39: 2 | F39: 557894.22 | G39: 558784.62 | H39: 10 | I39: =G39-F39-H39 -> 880.4 | J39: 10.99 | K39: =I39*J39 -> 9675.596
A40: 45845 | B40: Monday | C40: RITA001 | D40: AGO002 | E40: 1 | F40: 285282.38 | G40: 285376 | H40: 10 | I40: =G40-F40-H40 -> 83.62 | J40: 12.99 | K40: =I40*J40 -> 1086.2238
A41: 45845 | B41: Monday | C41: BLESS004 | D41: AGO002 | E41: 2 | F41: 408155.21 | G41: 408221.82 | H41: 10 | I41: =G41-F41-H41 -> 56.61 | J41: 12.99 | K41: =I41*J41 -> 735.3639
A42: 45845 | B42: Monday | C42: BLESS004 | D42: AGO002 | E42: 3 | F42: 370421.35 | G42: 370914.65 | H42: 10 | I42: =G42-F42-H42 -> 483.3 | J42: 12.99 | K42: =I42*J42 -> 6278.067
A43: 45845 | B43: Monday | C43: BLESS004 | D43: AGO002 | E43: 4 | F43: 522689.76 | G43: 523046.66 | H43: 10 | I43: =G43-F43-H43 -> 346.9 | J43: 12.99 | K43: =I43*J43 -> 4506.231
A44: 45876 | B44: Tuesday | C44: BLESS004 | D44: PMS001 | E44: 1 | F44: 350963.05 | G44: 351281.48 | I44: =G44-F44-H44 -> 318.43 | J44: 11.6 | K44: =I44*J44 -> 3693.788 | L44: =K44+K45 -> 9210.632 | M44: =K46+K47+K48+K49 -> 21172.932 | N44: =SUM(L44:M44) -> 30383.564 | O44: 50 | U44: 500 | W44: =N44-O44-P44-Q44-R44-S44-T44-U44-V44 -> 29833.564 | X44: 29834 | Y44: =X44-W44 -> 0.436
A45: 45876 | B45: Tuesday | C45: BLESS004 | D45: AGO002 | E45: 2 | F45: 558784.62 | G45: 559260.21 | I45: =G45-F45-H45 -> 475.59 | J45: 11.6 | K45: =I45*J45 -> 5516.844
A46: 45876 | B46: Tuesday | C46: RITA001 | D46: AGO002 | E46: 1 | F46: 285376 | G46: 285638.91 | I46: =G46-F46-H46 -> 262.91 | J46: 13.2 | K46: =I46*J46 -> 3470.412
A47: 45876 | B47: Tuesday | C47: RITA001 | D47: AGO002 | E47: 2 | F47: 408221.82 | G47: 408895.35 | I47: =G47-F47-H47 -> 673.53 | J47: 13.2 | K47: =I47*J47 -> 8890.596
A48: 45876 | B48: Tuesday | C48: RITA001 | D48: AGO002 | E48: 3 | F48: 370914.65 | G48: 371451.08 | I48: =G48-F48-H48 -> 536.43 | J48: 13.2 | K48: =I48*J48 -> 7080.876
A49: 45876 | B49: Tuesday | C49: RITA001 | D49: AGO002 | E49: 4 | F49: 523046.66 | G49: 523177.8 | I49: =G49-F49-H49 -> 131.14 | J49: 13.2 | K49: =I49*J49 -> 1731.048
A50: 45907 | B50: Wednes | C50: SILAS003 | D50: PMS001 | E50: 1 | F50: 351281.48 | G50: 351819.42 | I50: =G50-F50-H50 -> 537.94 | J50: 11.6 | K50: =I50*J50 -> 6240.104 | L50: =K50+K51 -> 14402.328 | M50: =K52+K53+K54+K55 -> 14037.408 | N50: =SUM(L50:M50) -> 28439.736 | O50: 50 | V50: 4578 | W50: =N50-O50-P50-Q50-R50-S50-T50-U50-V50 -> 23811.736 | X50: 23833 | Y50: =X50-W50 -> 21.264
A51: 45907 | B51: Wednes | C51: SILAS003 | D51: PMS001 | E51: 2 | F51: 559260.21 | G51: 559963.85 | I51: =G51-F51-H51 -> 703.64 | J51: 11.6 | K51: =I51*J51 -> 8162.224
A52: 45907 | B52: Wednes | C52: ABI002 | D52: AGO002 | E52: 1 | F52: 285638.91 | G52: 285807.71 | I52: =G52-F52-H52 -> 168.8 | J52: 13.2 | K52: =I52*J52 -> 2228.16
A53: 45907 | B53: Wednes | C53: ABI002 | D53: AGO002 | E53: 2 | F53: 408895.35 | G53: 409269.45 | I53: =G53-F53-H53 -> 374.1 | J53: 13.2 | K53: =I53*J53 -> 4938.12
A54: 45907 | B54: Wednes | C54: ABI002 | D54: AGO002 | E54: 3 | F54: 371451.08 | G54: 371861.69 | I54: =G54-F54-H54 -> 410.61 | J54: 13.2 | K54: =I54*J54 -> 5420.052
A55: 45907 | B55: Wednes | C55: ABI002 | D55: AGO002 | E55: 4 | F55: 523177.8 | G55: 523287.73 | I55: =G55-F55-H55 -> 109.93 | J55: 13.2 | K55: =I55*J55 -> 1451.076
A56: 45937 | B56: Thursday | C56: ABI002 | D56: PMS001 | E56: 1 | F56: 351819.42 | G56: 352093.58 | I56: =G56-F56-H56 -> 274.16 | J56: 11.6 | K56: =I56*J56 -> 3180.256 | L56: =K56+K57 -> 11550.584 | M56: =K58+K59+K60+K61 -> 8369.724 | N56: =SUM(L56:M56) -> 19920.308 | O56: 50 | W56: =N56-O56-P56-Q56-R56-S56-T56-U56-V56 -> 19870.308 | X56: 19871 | Y56: =X56-W56 -> 0.692
A57: 45937 | B57: Thursday | C57: ABI002 | D57: PMS001 | E57: 2 | F57: 559963.85 | G57: 560685.43 | I57: =G57-F57-H57 -> 721.58 | J57: 11.6 | K57: =I57*J57 -> 8370.328
A58: 45937 | B58: Thursday | C58: SILAS003 | D58: AGO002 | E58: 1 | F58: 285807.71 | G58: 285866.82 | I58: =G58-F58-H58 -> 59.11 | J58: 13.2 | K58: =I58*J58 -> 780.252
A59: 45937 | B59: Thursday | C59: SILAS003 | D59: AGO002 | E59: 2 | F59: 409269.45 | G59: 409370.61 | I59: =G59-F59-H59 -> 101.16 | J59: 13.2 | K59: =I59*J59 -> 1335.312
A60: 45937 | B60: Thursday | C60: SILAS003 | D60: AGO002 | E60: 3 | F60: 371861.69 | G60: 372262.5 | I60: =G60-F60-H60 -> 400.81 | J60: 13.2 | K60: =I60*J60 -> 5290.692
A61: 45937 | B61: Thursday | C61: SILAS003 | D61: AGO002 | E61: 4 | F61: 523287.73 | G61: 523360.72 | I61: =G61-F61-H61 -> 72.99 | J61: 13.2 | K61: =I61*J61 -> 963.468
A62: 45968 | B62: Friday | C62: RITA001 | D62: PMS001 | E62: 1 | F62: 352093.58 | G62: 352682.88 | I62: =G62-F62-H62 -> 589.3 | J62: 11.6 | K62: =I62*J62 -> 6835.88 | L62: =K62+K63 -> 16975.208 | M62: =K64+K65+K66+K67 -> 6608.844 | N62: =SUM(L62:M62) -> 23584.052 | Q62: 10862 | W62: =N62-O62-P62-Q62-R62-S62-T62-U62-V62 -> 12722.052 | X62: 12723 | Y62: =X62-W62 -> 0.948
A63: 45968 | B63: Friday | C63: RITA001 | D63: PMS001 | E63: 2 | F63: 560685.43 | G63: 561559.51 | I63: =G63-F63-H63 -> 874.08 | J63: 11.6 | K63: =I63*J63 -> 10139.328
A64: 45968 | B64: Friday | C64: RITA001 | D64: AGO002 | E64: 1 | F64: 285866.82 | G64: 285908.28 | I64: =G64-F64-H64 -> 41.46 | J64: 13.2 | K64: =I64*J64 -> 547.272
A65: 45968 | B65: Friday | C65: BLESS004 | D65: AGO002 | E65: 2 | F65: 409370.61 | G65: 409456.23 | I65: =G65-F65-H65 -> 85.62 | J65: 13.2 | K65: =I65*J65 -> 1130.184
A66: 45968 | B66: Friday | C66: BLESS004 | D66: AGO002 | E66: 3 | F66: 372262.5 | G66: 372533.8 | I66: =G66-F66-H66 -> 271.3 | J66: 13.2 | K66: =I66*J66 -> 3581.16
A67: 45968 | B67: Friday | C67: BLESS004 | D67: AGO002 | E67: 4 | F67: 523360.72 | G67: 523463.01 | I67: =G67-F67-H67 -> 102.29 | J67: 13.2 | K67: =I67*J67 -> 1350.228
A68: 45998 | B68: Saturday | C68: BLESS004 | D68: PMS001 | E68: 1 | F68: 352682.88 | G68: 353158.13 | I68: =G68-F68-H68 -> 475.25 | J68: 11.6 | K68: =I68*J68 -> 5512.9 | L68: =K68+K69 -> 13570.956 | M68: =K70+K71+K72+K73 -> 3684.384 | N68: =SUM(L68:M68) -> 17255.34 | W68: =N68-O68-P68-Q68-R68-S68-T68-U68-V68 -> 17255.34 | X68: 17256 | Y68: =X68-W68 -> 0.66
A69: 45998 | B69: Saturday | C69: BLESS004 | D69: AGO002 | E69: 2 | F69: 561559.51 | G69: 562254.17 | I69: =G69-F69-H69 -> 694.66 | J69: 11.6 | K69: =I69*J69 -> 8058.056
A70: 45998 | B70: Saturday | C70: RITA001 | D70: AGO002 | E70: 1 | F70: 285908.28 | G70: 285908.28 | I70: =G70-F70-H70 -> 0 | J70: 13.2 | K70: =I70*J70 -> 0
A71: 45998 | B71: Saturday | C71: RITA001 | D71: AGO002 | E71: 2 | F71: 409456.23 | G71: 409456.23 | I71: =G71-F71-H71 -> 0 | J71: 13.2 | K71: =I71*J71 -> 0
A72: 45998 | B72: Saturday | C72: RITA001 | D72: AGO002 | E72: 3 | F72: 372533.8 | G72: 372723.57 | I72: =G72-F72-H72 -> 189.77 | J72: 13.2 | K72: =I72*J72 -> 2504.964
A73: 45998 | B73: Saturday | C73: RITA001 | D73: AGO002 | E73: 4 | F73: 523463.01 | G73: 523552.36 | I73: =G73-F73-H73 -> 89.35 | J73: 13.2 | K73: =I73*J73 -> 1179.42
A74: 13/07/2025 | B74: Sunday | C74: SILAS003 | D74: PMS001 | E74: 1 | F74: 353158.13 | G74: 353628.01 | I74: =G74-F74-H74 -> 469.88 | J74: 11.6 | K74: =I74*J74 -> 5450.608 | L74: =K74+K75 -> 13291.86 | M74: =K76+K77+K78+K79 -> 6818.328 | N74: =SUM(L74:M74) -> 20110.188 | O74: 50 | W74: =N74-O74-P74-Q74-R74-S74-T74-U74-V74 -> 20060.188 | X74: 20061 | Y74: =X74-W74 -> 0.812
A75: 13/07/2025 | B75: Sunday | C75: SILAS003 | D75: PMS001 | E75: 2 | F75: 562254.17 | G75: 562930.14 | I75: =G75-F75-H75 -> 675.97 | J75: 11.6 | K75: =I75*J75 -> 7841.252
A76: 13/07/2025 | B76: Sunday | C76: ABI002 | D76: AGO002 | E76: 1 | F76: 285908.28 | G76: 286101.47 | I76: =G76-F76-H76 -> 193.19 | J76: 13.2 | K76: =I76*J76 -> 2550.108
A77: 13/07/2025 | B77: Sunday | C77: ABI002 | D77: AGO002 | E77: 2 | F77: 409456.23 | G77: 409535.76 | I77: =G77-F77-H77 -> 79.53 | J77: 13.2 | K77: =I77*J77 -> 1049.796
A78: 13/07/2025 | B78: Sunday | C78: ABI002 | D78: AGO002 | E78: 3 | F78: 372723.57 | G78: 372802.7 | I78: =G78-F78-H78 -> 79.13 | J78: 13.2 | K78: =I78*J78 -> 1044.516
A79: 13/07/2025 | B79: Sunday | C79: ABI002 | D79: AGO002 | E79: 4 | F79: 523552.36 | G79: 523717.05 | I79: =G79-F79-H79 -> 164.69 | J79: 13.2 | K79: =I79*J79 -> 2173.908
A80: 14/07/2025 | B80: Monday | C80: ABI002 | D80: PMS001 | E80: 1 | F80: 353628.01 | G80: 354144.98 | H80: 10 | I80: =G80-F80-H80 -> 506.97 | J80: 11.6 | K80: =I80*J80 -> 5880.852 | L80: =K80+K81 -> 15985.38 | M80: =K82+K83+K84+K85 -> 10366.356 | N80: =SUM(L80:M80) -> 26351.736 | O80: 50 | U80: 400 | W80: =N80-O80-P80-Q80-R80-S80-T80-U80-V80 -> 25901.736 | X80: 25901 | Y80: =X80-W80 -> -0.736
A81: 14/07/2025 | B81: Monday | C81: ABI002 | D81: PMS001 | E81: 2 | F81: 562930.16 | G81: 563811.24 | H81: 10 | I81: =G81-F81-H81 -> 871.08 | J81: 11.6 | K81: =I81*J81 -> 10104.528
A82: 14/07/2025 | B82: Monday | C82: SILAS003 | D82: AGO002 | E82: 1 | F82: 286101.47 | G82: 286462.86 | H82: 10 | I82: =G82-F82-H82 -> 351.39 | J82: 13.2 | K82: =I82*J82 -> 4638.348
A83: 14/07/2025 | B83: Monday | C83: SILAS003 | D83: AGO002 | E83: 2 | F83: 409535.76 | G83: 409641.07 | H83: 10 | I83: =G83-F83-H83 -> 95.31 | J83: 13.2 | K83: =I83*J83 -> 1258.092
A84: 14/07/2025 | B84: Monday | C84: SILAS003 | D84: AGO002 | E84: 3 | F84: 372802.7 | G84: 372979.99 | H84: 10 | I84: =G84-F84-H84 -> 167.29 | J84: 13.2 | K84: =I84*J84 -> 2208.228
A85: 14/07/2025 | B85: Monday | C85: SILAS003 | D85: AGO002 | E85: 4 | F85: 523717.05 | G85: 523898.39 | H85: 10 | I85: =G85-F85-H85 -> 171.34 | J85: 13.2 | K85: =I85*J85 -> 2261.688
A86: 15/07/2025 | B86: Tuesday | C86: RITA001 | D86: PMS001 | E86: 1 | F86: 354144.98 | G86: 355000.77 | I86: =G86-F86-H86 -> 855.79 | J86: 11.6 | K86: =I86*J86 -> 9927.164 | L86: =K86+K87 -> 25733.208 | M86: =K88+K89+K90+K91 -> 26739.24 | N86: =SUM(L86:M86) -> 52472.448 | O86: 50 | V86: 900 | W86: =N86-O86-P86-Q86-R86-S86-T86-U86-V86 -> 51522.448 | X86: 51523 | Y86: =X86-W86 -> 0.552
A87: 15/07/2025 | B87: Tuesday | C87: RITA001 | D87: PMS001 | E87: 2 | F87: 563811.24 | G87: 565173.83 | I87: =G87-F87-H87 -> 1362.59 | J87: 11.6 | K87: =I87*J87 -> 15806.044
A88: 15/07/2025 | B88: Tuesday | C88: RITA001 | D88: AGO002 | E88: 1 | F88: 286462.86 | G88: 286663.67 | I88: =G88-F88-H88 -> 200.81 | J88: 13.2 | K88: =I88*J88 -> 2650.692
A89: 15/07/2025 | B89: Tuesday | C89: BLESS004 | D89: AGO002 | E89: 2 | F89: 409641.07 | G89: 410201.19 | I89: =G89-F89-H89 -> 560.12 | J89: 13.2 | K89: =I89*J89 -> 7393.584
A90: 15/07/2025 | B90: Tuesday | C90: BLESS004 | D90: AGO002 | E90: 3 | F90: 372979.99 | G90: 373610.26 | I90: =G90-F90-H90 -> 630.27 | J90: 13.2 | K90: =I90*J90 -> 8319.564
A91: 15/07/2025 | B91: Tuesday | C91: BLESS004 | D91: AGO002 | E91: 4 | F91: 523898.39 | G91: 524532.89 | I91: =G91-F91-H91 -> 634.5 | J91: 13.2 | K91: =I91*J91 -> 8375.4
A92: 16/07/2025 | B92: Wednes | C92: BLESS004 | D92: PMS001 | E92: 1 | F92: 355000.77 | G92: 355261.57 | I92: =G92-F92-H92 -> 260.8 | J92: 12.6 | K92: =I92*J92 -> 3286.08 | L92: =K92+K93 -> 8797.446 | M92: =K94+K95+K96+K97 -> 5315.202 | N92: =SUM(L92:M92) -> 14112.648 | O92: 50 | W92: =N92-O92-P92-Q92-R92-S92-T92-U92-V92 -> 14062.648 | X92: 14063 | Y92: =X92-W92 -> 0.352
A93: 16/07/2025 | B93: Wednes | C93: BLESS004 | D93: AGO002 | E93: 2 | F93: 565173.83 | G93: 565611.24 | I93: =G93-F93-H93 -> 437.41 | J93: 12.6 | K93: =I93*J93 -> 5511.366
A94: 16/07/2025 | B94: Wednes | C94: RITA001 | D94: AGO002 | E94: 1 | F94: 286663.67 | G94: 286706.98 | I94: =G94-F94-H94 -> 43.31 | J94: 14.2 | K94: =I94*J94 -> 615.002
A95: 16/07/2025 | B95: Wednes | C95: RITA001 | D95: AGO002 | E95: 2 | F95: 410201.19 | G95: 410345.59 | I95: =G95-F95-H95 -> 144.4 | J95: 14.2 | K95: =I95*J95 -> 2050.48
A96: 16/07/2025 | B96: Wednes | C96: RITA001 | D96: AGO002 | E96: 3 | F96: 373610.26 | G96: 373780.66 | I96: =G96-F96-H96 -> 170.4 | J96: 14.2 | K96: =I96*J96 -> 2419.68
A97: 16/07/2025 | B97: Wednes | C97: RITA001 | D97: AGO002 | E97: 4 | F97: 524532.89 | G97: 524549.09 | I97: =G97-F97-H97 -> 16.2 | J97: 14.2 | K97: =I97*J97 -> 230.04
A98: 17/07/2025 | B98: Thursday | C98: SILAS003 | D98: PMS001 | E98: 1 | F98: 355261.57 | G98: 355891.01 | I98: =G98-F98-H98 -> 629.44 | J98: 12.6 | K98: =I98*J98 -> 7930.944 | L98: =K98+K99 -> 16942.338 | M98: =K100+K101+K102+K103 -> 7490.5 | N98: =SUM(L98:M98) -> 24432.838 | O98: 50 | U98: 2150 | W98: =N98-O98-P98-Q98-R98-S98-T98-U98-V98 -> 22232.838 | X98: 22233 | Y98: =X98-W98 -> 0.162
A99: 17/07/2025 | B99: Thursday | C99: SILAS003 | D99: PMS001 | E99: 2 | F99: 565611.24 | G99: 566326.43 | I99: =G99-F99-H99 -> 715.19 | J99: 12.6 | K99: =I99*J99 -> 9011.394
A100: 17/07/2025 | B100: Thursday | C100: ABI002 | D100: AGO002 | E100: 1 | F100: 286706.98 | G100: 286882.35 | I100: =G100-F100-H100 -> 175.37 | J100: 14.2 | K100: =I100*J100 -> 2490.254
...
